wasabi/__init__.py
wasabi/compat.py
wasabi/markdown.py
wasabi/printer.py
wasabi/tables.py
wasabi/traceback_printer.py
wasabi/util.py
wasabi/tests/__init__.py
wasabi/tests/test_jupyter.py
wasabi/tests/test_markdown.py
wasabi/tests/test_printer.py
wasabi/tests/test_tables.py
wasabi/tests/test_traceback.py
wasabi/tests/test_util.py
wasabi/tests/test-data/wasabi-test-notebook.ipynb
wasabi-1.1.2.dist-info/LICENSE
wasabi-1.1.2.dist-info/METADATA
wasabi-1.1.2.dist-info/WHEEL
wasabi-1.1.2.dist-info/top_level.txt
wasabi-1.1.2.dist-info/zip-safe
wasabi-1.1.2.dist-info/RECORD
