Metadata-Version: 2.1
Name: wasabi
Version: 1.1.2
Summary: A lightweight console printing and formatting toolkit
Home-page: https://github.com/explosion/wasabi
Author: Explosion
Author-email: contact@explosion.ai
License: MIT
Requires-Python: >=3.6
License-File: LICENSE
